hfo_py
