Metadata-Version: 1.0
Name: hfo-py
Version: 0.2
Summary: Half Field Offense in 2D RoboCup Soccer.
Home-page: UNKNOWN
Author: Matthew Hausknecht
Author-email: matthew.hausknecht@gmail.com
License: UNKNOWN
Platform: UNKNOWN
